Metadata-Version: 2.1
Name: aperturecore
Version: 0.0.6
Summary: A (unofficial) package for our Aperture Science Cores (tm)
Home-page: https://github.com/LazyNeko1/ApertureCore
Author: LazyNeko
Author-email: lazynekoo@gmail.com
License: UNKNOWN
Platform: UNKNOWN
Classifier: Programming Language :: Python :: 3
Classifier: License :: OSI Approved :: MIT License
Classifier: Operating System :: OS Independent
Requires-Python: >=3.6
